datasetsDynamic/__init__.py
datasetsDynamic/_modidx.py
datasetsDynamic/loadDataBakery.py
datasetsDynamic/loadDataYaz.py
datasetsDynamic/utils.py
datasetsDynamic/datasets/dataBakery_unprocessed.csv
datasetsDynamic/datasets/dataYaz_unprocessed.csv
datasetsDynamic-0.0.6.dist-info/LICENSE
datasetsDynamic-0.0.6.dist-info/METADATA
datasetsDynamic-0.0.6.dist-info/WHEEL
datasetsDynamic-0.0.6.dist-info/entry_points.txt
datasetsDynamic-0.0.6.dist-info/top_level.txt
datasetsDynamic-0.0.6.dist-info/RECORD
