Metadata-Version: 2.1
Name: datasetsDynamic
Version: 0.0.6
Summary: A package to load datasets for benchmarking prescriptive analytics approaches dynamically
Home-page: https://github.com/kaiguender/datasetsDynamic
Author: kaiguender
Author-email: kai.guender@yahoo.de
License: Apache Software License 2.0
Keywords: nbdev jupyter notebook python
Classifier: Development Status :: 4 - Beta
Classifier: Intended Audience :: Developers
Classifier: Natural Language :: English
Classifier: Programming Language :: Python :: 3.7
Classifier: Programming Language :: Python :: 3.8
Classifier: Programming Language :: Python :: 3.9
Classifier: Programming Language :: Python :: 3.10
Classifier: License :: OSI Approved :: Apache Software License
Requires-Python: >=3.7
License-File: LICENSE
Requires-Dist: fastcore (>=1.5.27)
Requires-Dist: pandas (>=1.3.0)
Requires-Dist: tsfresh (>=0.18.0)
Provides-Extra: dev
